spaceone/__init__.py
spaceone/core/__init__.py
spaceone/core/base.py
spaceone/core/command.py
spaceone/core/error.py
spaceone/core/locator.py
spaceone/core/manager.py
spaceone/core/token.py
spaceone/core/transaction.py
spaceone/core/utils.py
spaceone/core/auth/__init__.py
spaceone/core/auth/jwt/__init__.py
spaceone/core/auth/jwt/jwt_util.py
spaceone/core/cache/__init__.py
spaceone/core/cache/local_cache.py
spaceone/core/cache/redis_cache.py
spaceone/core/config/__init__.py
spaceone/core/config/default_conf.py
spaceone/core/connector/__init__.py
spaceone/core/connector/space_connector.py
spaceone/core/extension/__init__.py
spaceone/core/extension/grpc_health.py
spaceone/core/extension/server_info.py
spaceone/core/fastapi/__init__.py
spaceone/core/fastapi/api.py
spaceone/core/fastapi/server.py
spaceone/core/fastapi/extension/__init__.py
spaceone/core/fastapi/extension/health.py
spaceone/core/fastapi/extension/reflection.py
spaceone/core/handler/__init__.py
spaceone/core/handler/authentication_api_key_handler.py
spaceone/core/handler/authentication_handler.py
spaceone/core/handler/authorization_handler.py
spaceone/core/handler/event_handler.py
spaceone/core/handler/mutation_handler.py
spaceone/core/logger/__init__.py
spaceone/core/logger/filters/__init__.py
spaceone/core/logger/filters/error.py
spaceone/core/logger/filters/exclude.py
spaceone/core/logger/filters/masking.py
spaceone/core/logger/filters/message.py
spaceone/core/logger/filters/parameter.py
spaceone/core/logger/filters/traceback.py
spaceone/core/logger/filters/transaction.py
spaceone/core/model/__init__.py
spaceone/core/model/mongo_model/__init__.py
spaceone/core/model/mongo_model/filter_operator.py
spaceone/core/model/mongo_model/stat_operator.py
spaceone/core/pygrpc/__init__.py
spaceone/core/pygrpc/api.py
spaceone/core/pygrpc/client.py
spaceone/core/pygrpc/message_type.py
spaceone/core/pygrpc/server.py
spaceone/core/queue/__init__.py
spaceone/core/queue/redis_queue.py
spaceone/core/scheduler/__init__.py
kt_ds_core-0.0.1.dist-info/METADATA
kt_ds_core-0.0.1.dist-info/WHEEL
kt_ds_core-0.0.1.dist-info/entry_points.txt
kt_ds_core-0.0.1.dist-info/top_level.txt
kt_ds_core-0.0.1.dist-info/RECORD
