Metadata-Version: 2.1
Name: kt-ds-core
Version: 0.0.1
Summary: kt-ds core library
Home-page: 
Author: 
Author-email: 
License: Apache License 2.0
Requires-Dist: protobuf (==3.*)
Requires-Dist: grpcio-reflection
Requires-Dist: google-api-core
Requires-Dist: grpcio-health-checking
Requires-Dist: asyncio
Requires-Dist: PyYAML
Requires-Dist: unittest-xml-reporting (>=3.0.0)
Requires-Dist: pycryptodome
Requires-Dist: schedule
Requires-Dist: cachetools
Requires-Dist: jwcrypto
Requires-Dist: python-jose
Requires-Dist: factory-boy
Requires-Dist: jsonschema
Requires-Dist: python-dateutil
Requires-Dist: python-consul
Requires-Dist: scheduler-cron
Requires-Dist: click
Requires-Dist: uvicorn
Requires-Dist: fastapi
Requires-Dist: fastapi-utils
Requires-Dist: dnspython
Requires-Dist: pydantic
